[
  {
    "name": "Studded Leather",
    "type": "Light Armor",
    "cost_normal": "45 gp",
    "cost_cheap": "33 gp",
    "cost_expensive": "68 gp",
    "limited_stock": true,
    "rural_locale": false,
    "urban_locale": false,
    "premium_locale": true
  },
  {
    "name": "Chain Shirt",
    "type": "Medium Armor",
    "cost_normal": "50 gp",
    "cost_cheap": "38 gp",
    "cost_expensive": "75 gp",
    "limited_stock": false,
    "rural_locale": true,
    "urban_locale": true,
    "premium_locale": true
  },
  {
    "name": "Scale Mail",
    "type": "Medium Armor",
    "cost_normal": "50 gp",
    "cost_cheap": "38 gp",
    "cost_expensive": "75 gp",
    "limited_stock": true,
    "rural_locale": true,
    "urban_locale": true,
    "premium_locale": true
  },
  {
    "name": "Breastplate",
    "type": "Medium Armor",
    "cost_normal": "400 gp",
    "cost_cheap": "300 gp",
    "cost_expensive": "600 gp",
    "limited_stock": true,
    "rural_locale": false,
    "urban_locale": true,
    "premium_locale": true
  },
  {
    "name": "Half Plate",
    "type": "Medium Armor",
    "cost_normal": "750 gp",
    "cost_cheap": "562 gp",
    "cost_expensive": "1125 gp",
    "limited_stock": true,
    "rural_locale": false,
    "urban_locale": false,
    "premium_locale": true
  },
  {
    "name": "Ring Mail",
    "type": "Heavy Armor",
    "cost_normal": "30 gp",
    "cost_cheap": "22 gp",
    "cost_expensive": "45 gp",
    "limited_stock": true,
    "rural_locale": false,
    "urban_locale": true,
    "premium_locale": true
  },
  {
    "name": "Chain Mail",
    "type": "Heavy Armor",
    "cost_normal": "75 gp",
    "cost_cheap": "56 gp",
    "cost_expensive": "113 gp",
    "limited_stock": true,
    "rural_locale": true,
    "urban_locale": true,
    "premium_locale": true
  },
  {
    "name": "Splint",
    "type": "Heavy Armor",
    "cost_normal": "200 gp",
    "cost_cheap": "150 gp",
    "cost_expensive": "300 gp",
    "limited_stock": true,
    "rural_locale": false,
    "urban_locale": true,
    "premium_locale": true
  },
  {
    "name": "Plate",
    "type": "Heavy Armor",
    "cost_normal": "1500 gp",
    "cost_cheap": "1125 gp",
    "cost_expensive": "2250 gp",
    "limited_stock": true,
    "rural_locale": false,
    "urban_locale": true,
    "premium_locale": true
  },
  {
    "name": "Shield",
    "type": "Shield",
    "cost_normal": "10 gp",
    "cost_cheap": "7 gp",
    "cost_expensive": "15 gp",
    "limited_stock": true,
    "rural_locale": true,
    "urban_locale": true,
    "premium_locale": true
  },
  {
    "name": "Dagger",
    "type": "Simple Melee Weapon",
    "cost_normal": "2 gp",
    "cost_cheap": "1 gp",
    "cost_expensive": "3 gp",
    "limited_stock": true,
    "rural_locale": false,
    "urban_locale": true,
    "premium_locale": true
  },
  {
    "name": "Handaxe",
    "type": "Simple Melee Weapon",
    "cost_normal": "5 gp",
    "cost_cheap": "3 gp",
    "cost_expensive": "8 gp",
    "limited_stock": true,
    "rural_locale": false,
    "urban_locale": true,
    "premium_locale": true
  },
  {
    "name": "Javelin",
    "type": "Simple Melee Weapon",
    "cost_normal": "5 gp",
    "cost_cheap": "3 gp",
    "cost_expensive": "8 gp",
    "limited_stock": true,
    "rural_locale": true,
    "urban_locale": true,
    "premium_locale": true
  },
  {
    "name": "Light Hammer",
    "type": "Simple Melee Weapon",
    "cost_normal": "2 gp",
    "cost_cheap": "1 gp",
    "cost_expensive": "3 gp",
    "limited_stock": true,
    "rural_locale": false,
    "urban_locale": true,
    "premium_locale": true
  },
  {
    "name": "Mace",
    "type": "Simple Melee Weapon",
    "cost_normal": "5 gp",
    "cost_cheap": "3 gp",
    "cost_expensive": "8 gp",
    "limited_stock": true,
    "rural_locale": false,
    "urban_locale": true,
    "premium_locale": true
  },
  {
    "name": "Sickle",
    "type": "Simple Melee Weapon",
    "cost_normal": "1 gp",
    "cost_cheap": "7 sp",
    "cost_expensive": "2 gp",
    "limited_stock": true,
    "rural_locale": false,
    "urban_locale": true,
    "premium_locale": true
  },
  {
    "name": "Spear",
    "type": "Simple Melee Weapon",
    "cost_normal": "1 gp",
    "cost_cheap": "7 sp",
    "cost_expensive": "2 gp",
    "limited_stock": true,
    "rural_locale": true,
    "urban_locale": true,
    "premium_locale": true
  },
  {
    "name": "Battleaxe",
    "type": "Martial Melee Weapon",
    "cost_normal": "10 gp",
    "cost_cheap": "7 gp",
    "cost_expensive": "15 gp",
    "limited_stock": true,
    "rural_locale": false,
    "urban_locale": true,
    "premium_locale": true
  },
  {
    "name": "Flail",
    "type": "Martial Melee Weapon",
    "cost_normal": "10 gp",
    "cost_cheap": "7 gp",
    "cost_expensive": "15 gp",
    "limited_stock": true,
    "rural_locale": false,
    "urban_locale": true,
    "premium_locale": true
  },
  {
    "name": "Glaive",
    "type": "Martial Melee Weapon",
    "cost_normal": "20 gp",
    "cost_cheap": "15 gp",
    "cost_expensive": "30 gp",
    "limited_stock": true,
    "rural_locale": false,
    "urban_locale": true,
    "premium_locale": true
  },
  {
    "name": "Greataxe",
    "type": "Martial Melee Weapon",
    "cost_normal": "30 gp",
    "cost_cheap": "22 gp",
    "cost_expensive": "45 gp",
    "limited_stock": true,
    "rural_locale": false,
    "urban_locale": true,
    "premium_locale": true
  },
  {
    "name": "Greatsword",
    "type": "Martial Melee Weapon",
    "cost_normal": "50 gp",
    "cost_cheap": "38 gp",
    "cost_expensive": "75 gp",
    "limited_stock": true,
    "rural_locale": false,
    "urban_locale": true,
    "premium_locale": true
  },
  {
    "name": "Halberd",
    "type": "Martial Melee Weapon",
    "cost_normal": "20 gp",
    "cost_cheap": "15 gp",
    "cost_expensive": "30 gp",
    "limited_stock": true,
    "rural_locale": false,
    "urban_locale": true,
    "premium_locale": true
  },
  {
    "name": "Lance",
    "type": "Martial Melee Weapon",
    "cost_normal": "10 gp",
    "cost_cheap": "7 gp",
    "cost_expensive": "15 gp",
    "limited_stock": true,
    "rural_locale": true,
    "urban_locale": true,
    "premium_locale": true
  },
  {
    "name": "Longsword",
    "type": "Martial Melee Weapon",
    "cost_normal": "15 gp",
    "cost_cheap": "11 gp",
    "cost_expensive": "22 gp",
    "limited_stock": true,
    "rural_locale": false,
    "urban_locale": true,
    "premium_locale": true
  },
  {
    "name": "Maul",
    "type": "Martial Melee Weapon",
    "cost_normal": "10 gp",
    "cost_cheap": "7 gp",
    "cost_expensive": "15 gp",
    "limited_stock": true,
    "rural_locale": true,
    "urban_locale": true,
    "premium_locale": true
  },
  {
    "name": "Morningstar",
    "type": "Martial Melee Weapon",
    "cost_normal": "15 gp",
    "cost_cheap": "11 gp",
    "cost_expensive": "22 gp",
    "limited_stock": true,
    "rural_locale": false,
    "urban_locale": true,
    "premium_locale": true
  },
  {
    "name": "Pike",
    "type": "Martial Melee Weapon",
    "cost_normal": "5 gp",
    "cost_cheap": "3 gp",
    "cost_expensive": "8 gp",
    "limited_stock": true,
    "rural_locale": true,
    "urban_locale": true,
    "premium_locale": true
  },
  {
    "name": "Rapier",
    "type": "Martial Melee Weapon",
    "cost_normal": "25 gp",
    "cost_cheap": "18 gp",
    "cost_expensive": "38 gp",
    "limited_stock": true,
    "rural_locale": false,
    "urban_locale": true,
    "premium_locale": true
  },
  {
    "name": "Scimitar",
    "type": "Martial Melee Weapon",
    "cost_normal": "25 gp",
    "cost_cheap": "18 gp",
    "cost_expensive": "38 gp",
    "limited_stock": true,
    "rural_locale": false,
    "urban_locale": true,
    "premium_locale": true
  },
  {
    "name": "Shortsword",
    "type": "Martial Melee Weapon",
    "cost_normal": "10 gp",
    "cost_cheap": "7 gp",
    "cost_expensive": "15 gp",
    "limited_stock": true,
    "rural_locale": false,
    "urban_locale": true,
    "premium_locale": true
  },
  {
    "name": "Trident",
    "type": "Martial Melee Weapon",
    "cost_normal": "5 gp",
    "cost_cheap": "3 gp",
    "cost_expensive": "8 gp",
    "limited_stock": true,
    "rural_locale": true,
    "urban_locale": true,
    "premium_locale": true
  },
  {
    "name": "War Pick",
    "type": "Martial Melee Weapon",
    "cost_normal": "5 gp",
    "cost_cheap": "3 gp",
    "cost_expensive": "8 gp",
    "limited_stock": true,
    "rural_locale": false,
    "urban_locale": true,
    "premium_locale": true
  },
  {
    "name": "Warhammer",
    "type": "Martial Melee Weapon",
    "cost_normal": "15 gp",
    "cost_cheap": "11 gp",
    "cost_expensive": "22 gp",
    "limited_stock": true,
    "rural_locale": false,
    "urban_locale": true,
    "premium_locale": true
  },
  {
    "name": "Ball Bearings (bag of 1,000)",
    "type": "Adventuring Gear",
    "cost_normal": "1 gp",
    "cost_cheap": "7 sp",
    "cost_expensive": "2 gp",
    "limited_stock": true,
    "rural_locale": false,
    "urban_locale": true,
    "premium_locale": true
  },
  {
    "name": "Bell",
    "type": "Adventuring Gear",
    "cost_normal": "1 gp",
    "cost_cheap": "7 sp",
    "cost_expensive": "2 gp",
    "limited_stock": true,
    "rural_locale": false,
    "urban_locale": true,
    "premium_locale": true
  },
  {
    "name": "Block and Tackle",
    "type": "Adventuring Gear",
    "cost_normal": "1 gp",
    "cost_cheap": "7 sp",
    "cost_expensive": "2 gp",
    "limited_stock": true,
    "rural_locale": false,
    "urban_locale": true,
    "premium_locale": true
  },
  {
    "name": "Chain (10 feet)",
    "type": "Adventuring Gear",
    "cost_normal": "5 gp",
    "cost_cheap": "3 gp",
    "cost_expensive": "8 gp",
    "limited_stock": true,
    "rural_locale": true,
    "urban_locale": true,
    "premium_locale": true
  },
  {
    "name": "Crowbar",
    "type": "Adventuring Gear",
    "cost_normal": "2 gp",
    "cost_cheap": "1 gp",
    "cost_expensive": "3 gp",
    "limited_stock": true,
    "rural_locale": false,
    "urban_locale": true,
    "premium_locale": true
  },
  {
    "name": "Grappling Hook",
    "type": "Adventuring Gear",
    "cost_normal": "2 gp",
    "cost_cheap": "1 gp",
    "cost_expensive": "3 gp",
    "limited_stock": true,
    "rural_locale": false,
    "urban_locale": true,
    "premium_locale": true
  },
  {
    "name": "Hammer",
    "type": "Adventuring Gear",
    "cost_normal": "1 gp",
    "cost_cheap": "7 sp",
    "cost_expensive": "2 gp",
    "limited_stock": true,
    "rural_locale": false,
    "urban_locale": true,
    "premium_locale": true
  },
  {
    "name": "Hammer, Sledge",
    "type": "Adventuring Gear",
    "cost_normal": "2 gp",
    "cost_cheap": "1 gp",
    "cost_expensive": "3 gp",
    "limited_stock": true,
    "rural_locale": false,
    "urban_locale": true,
    "premium_locale": true
  },
  {
    "name": "Hunting Trap",
    "type": "Adventuring Gear",
    "cost_normal": "5 gp",
    "cost_cheap": "3 gp",
    "cost_expensive": "8 gp",
    "limited_stock": true,
    "rural_locale": false,
    "urban_locale": true,
    "premium_locale": true
  },
  {
    "name": "Lamp",
    "type": "Adventuring Gear",
    "cost_normal": "5 sp",
    "cost_cheap": "3 sp",
    "cost_expensive": "8 sp",
    "limited_stock": true,
    "rural_locale": false,
    "urban_locale": true,
    "premium_locale": true
  },
  {
    "name": "Lantern, Bullseye",
    "type": "Adventuring Gear",
    "cost_normal": "10 gp",
    "cost_cheap": "7 gp",
    "cost_expensive": "15 gp",
    "limited_stock": true,
    "rural_locale": false,
    "urban_locale": true,
    "premium_locale": true
  },
  {
    "name": "Lantern, Hooded",
    "type": "Adventuring Gear",
    "cost_normal": "5 gp",
    "cost_cheap": "3 gp",
    "cost_expensive": "8 gp",
    "limited_stock": true,
    "rural_locale": true,
    "urban_locale": true,
    "premium_locale": true
  },
  {
    "name": "Lock",
    "type": "Adventuring Gear",
    "cost_normal": "10 gp",
    "cost_cheap": "7 gp",
    "cost_expensive": "15 gp",
    "limited_stock": true,
    "rural_locale": false,
    "urban_locale": true,
    "premium_locale": true
  },
  {
    "name": "Manacles",
    "type": "Adventuring Gear",
    "cost_normal": "2 gp",
    "cost_cheap": "1 gp",
    "cost_expensive": "3 gp",
    "limited_stock": true,
    "rural_locale": false,
    "urban_locale": true,
    "premium_locale": true
  },
  {
    "name": "Mirror, Steel",
    "type": "Adventuring Gear",
    "cost_normal": "5 gp",
    "cost_cheap": "3 gp",
    "cost_expensive": "8 gp",
    "limited_stock": true,
    "rural_locale": false,
    "urban_locale": true,
    "premium_locale": true
  },
  {
    "name": "Pick, Miner's",
    "cost_normal": "2 gp",
    "cost_cheap": "1 gp",
    "cost_expensive": "3 gp",
    "type": "Adventuring Gear",
    "limited_stock": true,
    "rural_locale": true,
    "urban_locale": true,
    "premium_locale": true
  },
  {
    "name": "Piton",
    "cost_normal": "5 cp",
    "cost_cheap": "3 cp",
    "cost_expensive": "8 cp",
    "type": "Adventuring Gear",
    "limited_stock": false,
    "rural_locale": true,
    "urban_locale": true,
    "premium_locale": true
  },
  {
    "name": "Pot, Iron",
    "cost_normal": "2 gp",
    "cost_cheap": "1 gp",
    "cost_expensive": "3 gp",
    "type": "Adventuring Gear",
    "limited_stock": false,
    "rural_locale": true,
    "urban_locale": false,
    "premium_locale": true
  },
  {
    "name": "Spikes, Iron",
    "cost_normal": "1 gp",
    "cost_cheap": "7 sp",
    "cost_expensive": "2 gp",
    "type": "Adventuring Gear",
    "limited_stock": false,
    "rural_locale": true,
    "urban_locale": true,
    "premium_locale": true
  },
  {
    "name": "Whetstone",
    "cost_normal": "1 cp",
    "cost_cheap": "1 cp",
    "cost_expensive": "2 cp",
    "type": "Adventuring Gear",
    "limited_stock": true,
    "rural_locale": true,
    "urban_locale": true,
    "premium_locale": true
  },
  {
    "name": "Carpenter's Tools",
    "cost_normal": "8 gp",
    "cost_cheap": "6 gp",
    "cost_expensive": "12 gp",
    "type": "Adventuring Gear",
    "limited_stock": false,
    "rural_locale": true,
    "urban_locale": true,
    "premium_locale": true
  },
  {
    "name": "Mason's Tools",
    "cost_normal": "10 gp",
    "cost_cheap": "7 gp",
    "cost_expensive": "15 gp",
    "type": "Adventuring Gear",
    "limited_stock": false,
    "rural_locale": true,
    "urban_locale": true,
    "premium_locale": true
  },
  {
    "name": "Smith's Tools",
    "cost_normal": "20 gp",
    "cost_cheap": "15 gp",
    "cost_expensive": "30 gp",
    "type": "Adventuring Gear",
    "limited_stock": true,
    "rural_locale": true,
    "urban_locale": true,
    "premium_locale": true
  },
  {
    "name": "Tinker's Tools",
    "cost_normal": "50 gp",
    "cost_cheap": "38 gp",
    "cost_expensive": "75 gp",
    "type": "Adventuring Gear",
    "limited_stock": true,
    "rural_locale": false,
    "urban_locale": true,
    "premium_locale": true
  },
  {
    "name": "Horn",
    "cost_normal": "3 gp",
    "cost_cheap": "2 gp",
    "cost_expensive": "5 gp",
    "type": "Adventuring Gear",
    "limited_stock": false,
    "rural_locale": true,
    "urban_locale": false,
    "premium_locale": true
  }
]
